{"ref":"0cc395a0-db3c-4e78-8811-f0284bf327ae","syncData":{"version":2,"machineId":"874a7517-64d4-4c43-9b01-30dfcdcbe86e","content":"{\"settings\":\"{\\r\\n    \\\"workbench.colorCustomizations\\\": {\\r\\n        \\\"editorUnnecessaryCode.border\\\": \\\"#e1ee00\\\"\\r\\n      },\\r\\n      \\\"editorUnnecessary.foreground\\\":\\\"true\\\",\\r\\n      \\r\\n    \\\"workbench.iconTheme\\\": \\\"helium-icon-theme\\\",\\r\\n    \\\"code-runner.clearPreviousOutput\\\": true,\\r\\n    \\\"editor.fontFamily\\\": \\\"CodeNewRoman NFM\\\",\\r\\n    \\\"code-runner.runInTerminal\\\": true,\\r\\n    \\\"bracketPairColorizer.depreciation-notice\\\": false,\\r\\n    \\\"editor.mouseWheelZoom\\\": true,\\r\\n    \\\"editor.fontLigatures\\\": true,\\r\\n    \\\"editor.bracketPairColorization.enabled\\\": true,\\r\\n    \\\"terminal.integrated.cursorStyle\\\": \\\"line\\\",\\r\\n    \\\"terminal.integrated.cursorWidth\\\": 2,\\r\\n    \\\"terminal.integrated.tabs.title\\\": \\\" ${task}${separator}${local}${separator}${cwdFolder}\\\",\\r\\n    \\\"python.linting.cwd\\\": \\\"\\\",\\r\\n    \\\"code-runner.cwd\\\": \\\" ${process}\\\",\\r\\n    \\\"debug.terminal.clearBeforeReusing\\\": true,\\r\\n    \\\"editor.minimap.enabled\\\": false,\\r\\n\\r\\n    \\\"emojisense.languages\\\": {\\r\\n        \\\"plaintext\\\": {\\r\\n            \\\"markupCompletionsEnabled\\\": true,\\r\\n            \\\"emojiDecoratorsEnabled\\\": true\\r\\n        },\\r\\n        \\\"javascript.validate.enable\\\": false,\\r\\n        \\\"abap\\\": true,\\r\\n        \\\"bat\\\": true,\\r\\n        \\\"bibtex\\\": true,\\r\\n        \\\"clojure\\\": true,\\r\\n        \\\"coffeescript\\\": true,\\r\\n        \\\"c\\\": true,\\r\\n        \\\"cpp\\\": true,\\r\\n        \\\"csharp\\\": true,\\r\\n        \\\"css\\\": true,\\r\\n        \\\"diff\\\": true,\\r\\n        \\\"dockerfile\\\": true,\\r\\n        \\\"fsharp\\\": true,\\r\\n        \\\"git-commit\\\": true,\\r\\n        \\\"git-rebase\\\": true,\\r\\n        \\\"go\\\": true,\\r\\n        \\\"groovy\\\": true,\\r\\n        \\\"handlebars\\\": true,\\r\\n        \\\"html\\\": true,\\r\\n        \\\"ini\\\": true,\\r\\n        \\\"java\\\": true,\\r\\n        \\\"javascript\\\": true,\\r\\n        \\\"javascriptreact\\\": true,\\r\\n        \\\"json\\\": true,\\r\\n        \\\"jsonc\\\": true,\\r\\n        \\\"latex\\\": true,\\r\\n        \\\"less\\\": true,\\r\\n        \\\"lua\\\": true,\\r\\n        \\\"makefile\\\": true,\\r\\n        \\\"markdown\\\": true,\\r\\n        \\\"objective-c\\\": true,\\r\\n        \\\"objective-cpp\\\": true,\\r\\n        \\\"perl6\\\": true,\\r\\n        \\\"php\\\": true,\\r\\n        \\\"powershell\\\": true,\\r\\n        \\\"jade\\\": true,\\r\\n        \\\"python\\\": true,\\r\\n        \\\"r\\\": true,\\r\\n        \\\"razor\\\": true,\\r\\n        \\\"ruby\\\": true,\\r\\n        \\\"rust\\\": true,\\r\\n        \\\"scss\\\": true,\\r\\n        \\\"sass\\\": true,\\r\\n        \\\"shaderlab\\\": true,\\r\\n        \\\"shellscript\\\": true,\\r\\n        \\\"sql\\\": true,\\r\\n        \\\"swift\\\": true,\\r\\n        \\\"typescript\\\": true,\\r\\n        \\\"typescriptreact\\\": true,\\r\\n        \\\"tex\\\": true,\\r\\n        \\\"vb\\\": true,\\r\\n        \\\"xml\\\": true,\\r\\n        \\\"xsl\\\": true,\\r\\n        \\\"yaml\\\": true\\r\\n    \\r\\n},\\r\\n\\\"tabnine.experimentalAutoImports\\\": true,\\r\\n\\\"git.autofetch\\\": true,\\r\\n\\\"explorer.confirmDelete\\\": false,\\r\\n\\\"terminal.integrated.defaultProfile.windows\\\": \\\"Git Bash\\\",\\r\\n\\r\\n// \\\"code-runner.executorMap\\\": {\\r\\n//     \\\"cpp\\\": \\\"cd $dirWithoutTrailingSlash && g++ -std=c++11 $fileName -o $fileNameWithoutExt && ./$fileNameWithoutExt\\\"\\r\\n// } //Also works\\r\\n\\r\\n\\\"code-runner.terminalRoot\\\": \\\"/\\\",\\r\\n\\\"C_Cpp.errorSquiggles\\\": \\\"Enabled\\\",\\r\\n\\\"C_Cpp.autocompleteAddParentheses\\\": true,\\r\\n\\\"diffEditor.ignoreTrimWhitespace\\\": false,\\r\\n\\\"customBulletPoints.BulletPointMode\\\": \\\"cycle\\\",\\r\\n\\\"C_Cpp.intelliSenseEngine\\\": \\\"Tag Parser\\\",\\r\\n\\\"files.autoSave\\\": \\\"afterDelay\\\",\\r\\n\\\"debug.onTaskErrors\\\": \\\"abort\\\",\\r\\n\\\"security.workspace.trust.untrustedFiles\\\": \\\"open\\\",\\r\\n\\\"workbench.startupEditor\\\": \\\"none\\\",\\r\\n\\\"editor.suggestSelection\\\": \\\"first\\\",\\r\\n\\\"vsintellicode.modify.editor.suggestSelection\\\": \\\"automaticallyOverrodeDefaultValue\\\",\\r\\n\\\"code-runner.ignoreSelection\\\": true,\\r\\n\\\"editor.autoClosingBrackets\\\": \\\"always\\\",\\r\\n\\\"editor.autoClosingQuotes\\\": \\\"always\\\",\\r\\n\\\"editor.guides.bracketPairs\\\": \\\"active\\\",\\r\\n\\\"sync.gist\\\": \\\"d6e2130bfa3821900d15ebea618777d5\\\",\\r\\n\\\"files.maxMemoryForLargeFilesMB\\\": 8000,\\r\\n\\\"explorer.confirmDragAndDrop\\\": false,\\r\\n\\\"git.enableSmartCommit\\\": true,\\r\\n\\\"gitignore.cacheExpirationInterval\\\": 36000,\\r\\n\\\"files.exclude\\\": {\\r\\n    \\\"**/.classpath\\\": true,\\r\\n    \\\"**/.project\\\": true,\\r\\n    \\\"**/.settings\\\": true,\\r\\n    \\\"**/.factorypath\\\": true\\r\\n},\\r\\n\\\"liveServer.settings.donotShowInfoMsg\\\": true,\\r\\n\\\"[javascript]\\\": {\\r\\n    \\\"editor.defaultFormatter\\\": \\\"esbenp.prettier-vscode\\\"\\r\\n},\\r\\n\\\"C_Cpp.addNodeAddonIncludePaths\\\": true,\\r\\n\\\"[markdown]\\\": {\\r\\n    \\\"editor.defaultFormatter\\\": \\\"DavidAnson.vscode-markdownlint\\\"\\r\\n},\\r\\n\\\"terminal.integrated.fontSize\\\": 15,\\r\\n\\\"helium-icon-theme.folders.color\\\": \\\"#f64c55\\\",\\r\\n\\\"bracketPairColorizer.timeOut\\\": 2,\\r\\n\\\"helium-icon-theme.activeIconPack\\\": \\\"react\\\",\\r\\n\\\"helium-icon-theme.showWelcomeMessage\\\": false,\\r\\n\\\"C_Cpp.default.cppStandard\\\": \\\"c++23\\\",\\r\\n\\\"C_Cpp.default.cStandard\\\": \\\"c17\\\",\\r\\n\\\"C_Cpp.formatting\\\": \\\"clangFormat\\\",\\r\\n\\\"resmon.disk.format\\\": \\\"PercentRemaining\\\",\\r\\n\\\"helium-icon-theme.showReloadMessage\\\": false,\\r\\n\\\"editor.inlineSuggest.enabled\\\": true,\\r\\n\\\"liveServer.settings.CustomBrowser\\\": \\\"chrome\\\",\\r\\n\\\"terminal.integrated.gpuAcceleration\\\": \\\"off\\\",\\r\\n\\\"vscode_vibrancy.theme\\\": \\\"Default Dark\\\",\\r\\n\\\"extensions.ignoreRecommendations\\\": true,\\r\\n\\\"go.inlayHints.rangeVariableTypes\\\": true,\\r\\n\\\"vscode_vibrancy.opacity\\\": -100,\\r\\n\\\"redhat.telemetry.enabled\\\": true,\\r\\n\\\"editor.codeLensFontFamily\\\": \\\" \\\",\\r\\n\\\"[yaml]\\\": {\\r\\n    \\\"editor.defaultFormatter\\\": \\\"redhat.vscode-yaml\\\"\\r\\n},\\r\\n\\\"path-intellisense.autoSlashAfterDirectory\\\": true,\\r\\n\\\"path-intellisense.autoTriggerNextSuggestion\\\": true,\\r\\n\\\"path-intellisense.extensionOnImport\\\": true,\\r\\n\\\"path-intellisense.ignoreTsConfigBaseUrl\\\": true,\\r\\n\\\"path-intellisense.showHiddenFiles\\\": true,\\r\\n\\\"workbench.colorTheme\\\": \\\"GitHub Dark Dimmed\\\",\\r\\n\\\"C_Cpp.caseSensitiveFileSupport\\\": \\\"enabled\\\",\\r\\n\\\"C_Cpp.inlayHints.autoDeclarationTypes.enabled\\\": true,\\r\\n\\\"C_Cpp.inlayHints.autoDeclarationTypes.showOnLeft\\\": true,\\r\\n\\\"C_Cpp.inlayHints.parameterNames.enabled\\\": true,\\r\\n\\\"C_Cpp.inlayHints.referenceOperator.enabled\\\": true,\\r\\n\\\"resmon.show.cputemp\\\": true,\\r\\n\\\"php.memoryLimit\\\": \\\"6095M\\\",\\r\\n\\\"php-intellisense.trace.server\\\": \\\"verbose\\\",\\r\\n\\\"liveServer.settings.donotVerifyTags\\\": true,\\r\\n\\\"liveServer.settings.wait\\\": 1,\\r\\n\\\"css.trace.server\\\": \\\"verbose\\\",\\r\\n\\\"html.trace.server\\\": \\\"verbose\\\",\\r\\n\\\"liveServer.settings.port\\\": 3500,\\r\\n\\\"phpserver.relativePath\\\": \\\"\\\",\\r\\n\\\"liveServer.settings.fullReload\\\": true,\\r\\n\\\"liveServer.settings.useLocalIp\\\": true,\\r\\n\\\"workbench.sideBar.location\\\": \\\"right\\\",\\r\\n\\\"[html]\\\": {\\r\\n    \\\"editor.defaultFormatter\\\": \\\"mohd-akram.vscode-html-format\\\"\\r\\n},\\r\\n\\\"javascript.format.semicolons\\\": \\\"insert\\\",\\r\\n\\\"typescript.format.semicolons\\\": \\\"insert\\\",\\r\\n\\\"codesnap.boxShadow\\\": \\\"rgba(10, 10,10, 0.55) 0px 20px 68px\\\",\\r\\n\\\"codesnap.transparentBackground\\\": true,\\r\\n\\\"terminal.integrated.fontFamily\\\": \\\"monospace\\\",\\r\\n\\\"editor.fontSize\\\": 19\\r\\n\\r\\n \\r\\n  \\r\\n}\"}"}}